nplab/__init__.py
nplab/__main__.py
nplab/datafile.py
nplab/analysis/Auto_Gaussian_Smooth.py
nplab/analysis/SPC_to_h5.py
nplab/analysis/__init__.py
nplab/analysis/calculate_MPEs.py
nplab/analysis/ivium.py
nplab/analysis/laser-damage-threshold-calculator.py
nplab/analysis/mjh250-image-analysis.py
nplab/analysis/nanoparticle_tinder.py
nplab/analysis/signal_alignment.py
nplab/analysis/smoothing.py
nplab/analysis/spectral_processing.py
nplab/analysis/view_spectra_2018.py
nplab/analysis/wavelets.py
nplab/analysis/NPoM_Dark_Field_categorization/Analyse_Z_Scan.py
nplab/analysis/NPoM_Dark_Field_categorization/Condense_DF_Spectra.py
nplab/analysis/NPoM_Dark_Field_categorization/Condense_fit_DF.py
nplab/analysis/NPoM_Dark_Field_categorization/DF_Multipeakfit.py
nplab/analysis/NPoM_Dark_Field_categorization/DF_particleTracking_PL.py
nplab/analysis/NPoM_Dark_Field_categorization/__init__.py
nplab/analysis/SERS_Fitting/Auto_Fit_Raman.py
nplab/analysis/SERS_Fitting/Iterative_Raman_Fitting.py
nplab/analysis/SERS_Fitting/Peak_Fitting_UI.py
nplab/analysis/SERS_Fitting/Stokes_AntiStokes_Fitting.py
nplab/analysis/SERS_Fitting/__init__.py
nplab/analysis/SERS_Fitting/peaks_and_bg_fitting.py
nplab/analysis/example_data/__init__.py
nplab/analysis/live_plotting/__init__.py
nplab/experiment/__init__.py
nplab/experiment/experiment.py
nplab/experiment/gui.py
nplab/experiment/resources_rc.py
nplab/experiment/dynamic_light_scattering/__init__.py
nplab/experiment/dynamic_light_scattering/dls_signal_postprocessing.py
nplab/experiment/dynamic_light_scattering/dynamic_light_scattering.py
nplab/experiment/dynamic_light_scattering/multiangle-rig.py
nplab/experiment/fiber_raman/Pacton.py
nplab/experiment/fiber_raman/__init__.py
nplab/experiment/fiber_raman/calibration_file_creator.py
nplab/experiment/fiber_raman/calibration_generator.py
nplab/experiment/fiber_raman/datafile_format_loader.py
nplab/experiment/fiber_raman/experiment.py
nplab/experiment/fiber_raman/main.py
nplab-1.0.dist-info/License.md
nplab-1.0.dist-info/METADATA
nplab-1.0.dist-info/WHEEL
nplab-1.0.dist-info/top_level.txt
nplab-1.0.dist-info/RECORD
