Metadata-Version: 2.1
Name: nplab
Version: 1.0
Summary: NP lab equipment control
Home-page: UNKNOWN
Author: Alan Sanders
Author-email: as2180@cam.ac.uk
License: UNKNOWN
Platform: UNKNOWN
